Metadata-Version: 2.1
Name: dognamescli
Version: 1.0.2
Summary: Get Awesome Random dog names in CLI!
Home-page: https://yoginth.com
Author: Yoginth
Author-email: me@yoginth.com
License: UNKNOWN
Project-URL: Patreon, https://www.patreon.com/yoginth
Project-URL: Source, https://gitlab.com/yoginth/dognamescli
Platform: UNKNOWN
Classifier: Programming Language :: Python
Classifier: Natural Language :: English
Classifier: Environment :: Console
Classifier: Operating System :: OS Independent
Classifier: Intended Audience :: End Users/Desktop
Classifier: License :: OSI Approved :: MIT License
